classRant/__init__.py
classRant/classRant.py
classRant-1.0.dist-info/METADATA
classRant-1.0.dist-info/RECORD
classRant-1.0.dist-info/WHEEL
classRant-1.0.dist-info/top_level.txt
